{
  "title": "A little \"gem\" in Oakville",
  "description": "Such a little \"gem\" in Oakville with the soft white sand beach",
  "author": "JF",
  "image": "20190805",
  "body": ["&nbsp;",
           "&nbsp;<br /><img src='https://i.pinimg.com/originals/bf/19/bb/bf19bb39144848f109042100aad9b6a1.jpg' alt='20190630' style='width:100%' />",
           "&nbsp;<br /><img src='https://i.pinimg.com/originals/18/38/4e/18384ee4d28a4480843e7fb27b2b5970.jpg' alt='20190805-0' style='width:100%' />",
           "&nbsp;<br /><img src='https://i.pinimg.com/originals/04/94/ee/0494eee981f274c03cb1003779b5e7f5.jpg' alt='20190805-1' style='width:100%' />",
           "&nbsp;<br /><img src='https://i.pinimg.com/originals/6a/10/e6/6a10e638d1e3ff317acccc9fb70e8db2.jpg' alt='20190805-2' style='width:100%' />",
           "&nbsp;"],
  "publishedAt": "2019-08-05",
  "show": false
}
